CHANGES.md
MANIFEST.in
README.md
setup.py
django_geostore_routing.egg-info/PKG-INFO
django_geostore_routing.egg-info/SOURCES.txt
django_geostore_routing.egg-info/dependency_links.txt
django_geostore_routing.egg-info/requires.txt
django_geostore_routing.egg-info/top_level.txt
geostore_routing/VERSION.md
geostore_routing/__init__.py
geostore_routing/apps.py
geostore_routing/functions.py
geostore_routing/helpers.py
geostore_routing/settings.py
geostore_routing/tasks.py
geostore_routing/management/__init__.py
geostore_routing/management/commands/__init__.py
geostore_routing/management/commands/update_topology.py
geostore_routing/migrations/0001_initial.py
geostore_routing/migrations/__init__.py
geostore_routing/serializers/__init__.py
geostore_routing/serializers/mixins.py
geostore_routing/signals/__init__.py
geostore_routing/signals/handlers.py
geostore_routing/views/__init__.py
geostore_routing/views/mixins.py