Metadata-Version: 2.1
Name: django-geostore-routing
Version: 0.9.8
Summary: PGRouting plugin for django-geostore
Home-page: https://github.com/Terralego/django-geostore-routing.git
Author: Makina Corpus
Author-email: terralego-pypi@makina-corpus.com
License: UNKNOWN
Platform: UNKNOWN
Classifier: Environment :: Web Environment
Classifier: Framework :: Django
Classifier: Intended Audience :: Developers
Classifier: Topic :: Internet :: WWW/HTTP
Classifier: Topic :: Internet :: WWW/HTTP :: Dynamic Content
Classifier: License :: OSI Approved :: MIT License
Classifier: Natural Language :: English
Classifier: Operating System :: OS Independent
Classifier: Programming Language :: Python
Classifier: Programming Language :: Python :: 3.6
Classifier: Programming Language :: Python :: 3.7
Classifier: Programming Language :: Python :: 3.8
Provides-Extra: dev
